werkflow_encryption/__init__.py
werkflow_encryption/encryption.py
werkflow_encryption/exceptions/__init__.py
werkflow_encryption/exceptions/missing_encryption_key_error.py
werkflow_encryption-0.2.1.dist-info/licenses/LICENSE
werkflow_encryption-0.2.1.dist-info/METADATA
werkflow_encryption-0.2.1.dist-info/WHEEL
werkflow_encryption-0.2.1.dist-info/top_level.txt
werkflow_encryption-0.2.1.dist-info/RECORD
