Metadata-Version: 2.4
Name: werkflow-encryption
Version: 0.2.1
Summary: An encryption module for Werkflow powered by the Cryptography library.
Author-email: Ada Lundhe <adalundhe@lundhe.audio>
Keywords: pypi,cicd,python,werkflow,workflow,encryption
Classifier: Programming Language :: Python :: 3.11
Classifier: Programming Language :: Python :: 3.12
Classifier: Programming Language :: Python :: 3.13
Classifier: Operating System :: OS Independent
Requires-Python: >=3.11
License-File: LICENSE
Requires-Dist: werkflow-core
Requires-Dist: werkflow-file
Requires-Dist: werkflow-secrets
Requires-Dist: werkflow-shell
Requires-Dist: werkflow-system
Requires-Dist: cryptography
Dynamic: license-file
